{
  "foosball_players": [
    {
      "first_name": "Joel",
      "last_name": "Sims",
      "wins": 24,
      "losses": 22,
      "last_played": "Oct 05 2021",
      "avatar": "Avatar.jpg",
      "avatarThumb": "AvatarThumb.jpg"
    },
    {
      "first_name": "Winston",
      "last_name": "Boyd",
      "wins": 12,
      "losses": 36,
      "last_played": "Oct 04 2021",
      "avatar": "Avatar2.jpg",
      "avatarThumb": "Avatar2Thumb.jpg"
    },
    {
      "first_name": "Armando",
      "last_name": "Fitzgerald",
      "wins": 32,
      "losses": 12,
      "last_played": "Oct 02 2021",
      "avatar": "Avatar3.jpg",
      "avatarThumb": "Avatar3Thumb.jpg"
    },
    {
      "first_name": "Nicholas",
      "last_name": "Garner",
      "wins": 23,
      "losses": 32,
      "last_played": "Oct 05 2021",
      "avatar": "Avatar4.jpg",
      "avatarThumb": "Avatar4Thumb.jpg"
    },
    {
      "first_name": "Lynda",
      "last_name": "Ford",
      "wins": 27,
      "losses": 22,
      "last_played": "Oct 01 2021",
      "avatar": "Avatar.jpg",
      "avatarThumb": "Avatar5Thumb.jpg"
    },
    {
      "first_name": "Marvin",
      "last_name": "Pierce",
      "wins": 14,
      "losses": 26,
      "last_played": "Sep 29 2021",
      "avatar": "Avatar.jpg",
      "avatarThumb": "Avatar6Thumb.jpg"
    },
    {
      "first_name": "Leslie",
      "last_name": "Barber",
      "wins": 20,
      "losses": 16,
      "last_played": "Sep 30 2021",
      "avatar": "Avatar.jpg",
      "avatarThumb": "Avatar7Thumb.jpg"
    },
    {
      "first_name": "Nicole",
      "last_name": "Gilbert",
      "wins": 13,
      "losses": 37,
      "last_played": "Oct 05 2021",
      "avatar": "Avatar.jpg",
      "avatarThumb": "Avatar2Thumb.jpg"
    },
    {
      "first_name": "Gregg",
      "last_name": "Dean",
      "wins": 10,
      "losses": 32,
      "last_played": "Oct 03 2021",
      "avatar": "Avatar.jpg",
      "avatarThumb": "Avatar3Thumb.jpg"
    },
    {
      "first_name": "Brett",
      "last_name": "Griffith",
      "wins": 25,
      "losses": 25,
      "last_played": "Oct 02 2021",
      "avatar": "Avatar.jpg",
      "avatarThumb": "Avatar4Thumb.jpg"
    },
    {
      "first_name": "Michael",
      "last_name": "Warren",
      "wins": 26,
      "losses": 30,
      "last_played": "Oct 01 2021",
      "avatar": "Avatar.jpg",
      "avatarThumb": "Avatar5Thumb.jpg"
    },
    {
      "first_name": "Victor",
      "last_name": "Miller",
      "wins": 9,
      "losses": 42,
      "last_played": "Oct 03 2021",
      "avatar": "Avatar.jpg",
      "avatarThumb": "Avatar6Thumb.jpg"
    },
    {
      "first_name": "Kent",
      "last_name": "Nunez",
      "wins": 32,
      "losses": 13,
      "last_played": "Oct 05 2021",
      "avatar": "Avatar.jpg",
      "avatarThumb": "Avatar7Thumb.jpg"
    },
    {
      "first_name": "Dolores",
      "last_name": "Vega",
      "wins": 22,
      "losses": 27,
      "last_played": "Oct 02 2021",
      "avatar": "Avatar.jpg",
      "avatarThumb": "Avatar2Thumb.jpg"
    },
    {
      "first_name": "Ray",
      "last_name": "Briggs",
      "wins": 40,
      "losses": 12,
      "last_played": "Oct 03 2021",
      "avatar": "Avatar.jpg",
      "avatarThumb": "Avatar3Thumb.jpg"
    }
  ]
}